odoo/addons/maintenance_purchase/README.rst
odoo/addons/maintenance_purchase/__init__.py
odoo/addons/maintenance_purchase/__manifest__.py
odoo/addons/maintenance_purchase/i18n/it.po
odoo/addons/maintenance_purchase/i18n/maintenance_purchase.pot
odoo/addons/maintenance_purchase/models/__init__.py
odoo/addons/maintenance_purchase/models/maintenance_equipment.py
odoo/addons/maintenance_purchase/models/purchase_order.py
odoo/addons/maintenance_purchase/readme/CONTRIBUTORS.rst
odoo/addons/maintenance_purchase/readme/DESCRIPTION.rst
odoo/addons/maintenance_purchase/static/description/icon.png
odoo/addons/maintenance_purchase/static/description/index.html
odoo/addons/maintenance_purchase/views/maintenance_equipment.xml
odoo/addons/maintenance_purchase/views/purchase_order.xml
odoo14_addon_maintenance_purchase-14.0.1.0.2.dist-info/METADATA
odoo14_addon_maintenance_purchase-14.0.1.0.2.dist-info/WHEEL
odoo14_addon_maintenance_purchase-14.0.1.0.2.dist-info/top_level.txt
odoo14_addon_maintenance_purchase-14.0.1.0.2.dist-info/RECORD
